elifepubmed/__init__.py
elifepubmed/conf.py
elifepubmed/generate.py
elifepubmed/utils.py
elifepubmed-0.7.0.dist-info/LICENSE
elifepubmed-0.7.0.dist-info/METADATA
elifepubmed-0.7.0.dist-info/WHEEL
elifepubmed-0.7.0.dist-info/top_level.txt
elifepubmed-0.7.0.dist-info/RECORD
