Metadata-Version: 2.1
Name: elifepubmed
Version: 0.7.0
Summary: eLife PubMed deposit of journal articles.
Home-page: https://github.com/elifesciences/elife-pubmed-xml-generation
Maintainer: eLife Sciences Publications Ltd.
Maintainer-email: tech-team@elifesciences.org
License: MIT
Classifier: Development Status :: 3 - Alpha
Classifier: Intended Audience :: Developers
Classifier: License :: OSI Approved :: MIT License
Classifier: Programming Language :: Python :: 3
License-File: LICENSE
Requires-Dist: elifetools >=0.33.0
Requires-Dist: elifearticle >=0.16.0
Requires-Dist: configparser
Requires-Dist: PyYAML
